fastapi_lite_auth/__init__.py
fastapi_lite_auth/basics/basic_config.py
fastapi_lite_auth/basics/basic_models.py
fastapi_lite_auth/basics/basic_schemas.py
fastapi_lite_auth/module/auth_config.py
fastapi_lite_auth/module/auth_current_user.py
fastapi_lite_auth/module/auth_manager.py
fastapi_lite_auth/module/auth_router.py
fastapi_lite_auth-1.0.1.dist-info/METADATA
fastapi_lite_auth-1.0.1.dist-info/WHEEL
fastapi_lite_auth-1.0.1.dist-info/top_level.txt
fastapi_lite_auth-1.0.1.dist-info/RECORD
