Metadata-Version: 2.4
Name: fastapi_lite_auth
Version: 1.0.1
Summary: Simple login/password authentication module for FastAPI project.
Home-page: https://github.com/losos3000/fastapi-lite-auth
Author: losos3000
Author-email: andreygolikov.work@yandex.ru
Project-URL: GitHub, https://github.com/losos3000/fastapi-lite-auth
Keywords: fastapi auth authentication lite simple basic base
Classifier: Programming Language :: Python :: 3.13
Classifier: Operating System :: OS Independent
Requires-Python: >=3.13.0
Requires-Dist: authx>=1.4.2
Requires-Dist: fastapi>=0.115.12
Requires-Dist: pydantic>=2.11.4
Dynamic: author
Dynamic: author-email
Dynamic: classifier
Dynamic: description
Dynamic: description-content-type
Dynamic: home-page
Dynamic: keywords
Dynamic: project-url
Dynamic: requires-dist
Dynamic: requires-python
Dynamic: summary
